{
  "sensors":[
    {
      "name":"Room1 Temp",
      "driver":"Random",
      "config":{
        "min":"-10",
        "max":"35"
      },
      "interval":2,
      "enabled":"true"
    },
    {
      "name":"Ext temp1",
      "driver":"Random",
      "config":{
        "min":"0",
        "max":"20"
      },
      "interval":6,
      "enabled":"true"
    }
    ],
  "cloudService":{
    "driver":"HTTP",
    "host":"tbio.dcliclab.fr:8080",
    "credentials":"",
    "format":"",
    "target":"/api/v1/mZRxTrmhcRlOaFT94nom/telemetry",
    "enabled":"true"
  }
}